bospell/__init__.py
bospell/bospell.py
bospell/config.py
bospell/error.py
bospell/lm.py
bospell/text.py
bospell/tokenizers.py
bospell/utils.py
bospell/candidates/__init__.py
bospell/candidates/symspell.py
bospell/resources/dictionaries/general.txt
bospell-0.0.4.dist-info/METADATA
bospell-0.0.4.dist-info/WHEEL
bospell-0.0.4.dist-info/top_level.txt
bospell-0.0.4.dist-info/RECORD
