Metadata-Version: 2.1
Name: bospell
Version: 0.0.4
Summary: Spell checking toolkit for Tibetan (boyig)
Home-page: https://github.com/Esukhia/bospell
Author: Esukhia developers
Author-email: 10zin@esukhia.org
License: MIT
Platform: UNKNOWN
Requires-Python: >=3.8
Requires-Dist: botok (<1.0,>=0.8.6)
Requires-Dist: symspellpy (<7.0,>=6.7.0)
